langchain_sarvam/__init__.py
langchain_sarvam/chat_models.py
langchain_sarvam/py.typed
langchain_sarvam/version.py
langchain_sarvam-0.1.1.dist-info/METADATA
langchain_sarvam-0.1.1.dist-info/WHEEL
langchain_sarvam-0.1.1.dist-info/licenses/LICENSE
langchain_sarvam-0.1.1.dist-info/RECORD
