Metadata-Version: 2.4
Name: langchain_sarvam
Version: 0.1.1
Summary: An integration package connecting sarvam-AI and LangChain
Project-URL: Homepage, https://github.com/parth1609/langchain_sarvam
Project-URL: Repository, https://github.com/parth1609/langchain_sarvam
Author-email: Parth1609 <parthgajananpatil@gmail.com>
License-Expression: MIT
License-File: LICENSE
Keywords: ai,chat,langchain,llm,sarvam
Classifier: Development Status :: 4 - Beta
Classifier: Intended Audience :: Developers
Classifier: License :: OSI Approved :: MIT License
Requires-Python: >=3.9
Requires-Dist: langchain-core<1.0.0,>=0.3.15
Requires-Dist: python-dotenv>=1.0.0
Requires-Dist: sarvamai>=0.1.0
